clockcaptcha/__init__.py
clockcaptcha/__version__.py
clockcaptcha/captcha.py
clockcaptcha/config.py
clockcaptcha/helpers.py
clockcaptcha/numbers.py
clockcaptcha-0.1.3.dist-info/METADATA
clockcaptcha-0.1.3.dist-info/WHEEL
clockcaptcha-0.1.3.dist-info/licenses/LICENSE
clockcaptcha-0.1.3.dist-info/RECORD
