Metadata-Version: 2.3
Name: clockcaptcha
Version: 0.1.3
Summary: Dynamically generated, AI-resistant captcha images
Project-URL: Homepage, https://github.com/stefs304/clockcaptcha
Project-URL: Issues, https://github.com/stefs304/clockcaptcha/issues
Author: Stefan Stojanovic
License: MIT License
License-File: LICENSE
Keywords: captcha,captcha-generator,captcha-image,clock,digital,python
Classifier: License :: OSI Approved :: MIT License
Classifier: Operating System :: OS Independent
Classifier: Programming Language :: Python :: 3
Requires-Python: >=3.9
Requires-Dist: pillow
